rh_calculator/__init__.py
rh_calculator/esat.py
rh_calculator/humid.py
rh_calculator-0.0.1.dist-info/METADATA
rh_calculator-0.0.1.dist-info/WHEEL
rh_calculator-0.0.1.dist-info/top_level.txt
rh_calculator-0.0.1.dist-info/RECORD
